warp2/__init__.py
warp2/membrane.py
warp2/warp2.py
warp2/warper.py
warp2-0.1.1.dist-info/DESCRIPTION.rst
warp2-0.1.1.dist-info/METADATA
warp2-0.1.1.dist-info/RECORD
warp2-0.1.1.dist-info/WHEEL
warp2-0.1.1.dist-info/metadata.json
warp2-0.1.1.dist-info/top_level.txt
