Metadata-Version: 2.0
Name: warp2
Version: 0.1.1
Summary: use python2 modules in python3
Home-page: https://haarcuba.github.io/warp2/
Author: Yoav Kleinberger
Author-email: haarcuba@gmail.com
License: UNKNOWN
Keywords: subprocess
Platform: UNKNOWN
Classifier: Programming Language :: Python
Provides-Extra: testing
